{"data": {"request": [{"type": "IP", "query": "40.639801"}], "weather": [{"date": "2018-09-01", "astronomy": [{"sunrise": "07:02 AM", "sunset": "08:00 PM", "moonrise": "11:47 PM", "moonset": "12:54 PM", "moon_phase": "Waning Gibbous", "moon_illumination": "48"}], "maxtempC": "35", "maxtempF": "95", "mintempC": "25", "mintempF": "77", "avgtempC": "31", "avgtempF": "87", "totalSnow_cm": "0.0", "sunHour": "11.6", "uvIndex": "8", "hourly": [{"time": "24", "tempC": "35", "tempF": "95", "windspeedMiles": "15", "windspeedKmph": "25", "winddirDegree": "174", "winddir16Point": "S", "weatherCode": "113", "weatherIconUrl": [{"value": "http://cdn.worldweatheronline.com/images/wsymbols01_png_64/wsymbol_0001_sunny.png"}], "weatherDesc": [{"value": "Sunny"}], "precipMM": "0.1", "precipInches": "0.0", "humidity": "53", "visibility": "10", "visibilityMiles": "6", "pressure": "1011", "pressureInches": "30", "cloudcover": "6", "HeatIndexC": "31", "HeatIndexF": "88", "DewPointC": "18", "DewPointF": "65", "WindChillC": "30", "WindChillF": "85", "WindGustMiles": "22", "WindGustKmph": "36", "FeelsLikeC": "31", "FeelsLikeF": "88", "uvIndex": "8"}]}, {"date": "2018-09-02", "astronomy": [{"sunrise": "07:02 AM", "sunset": "07:59 PM", "moonrise": "No moonrise", "moonset": "01:58 PM", "moon_phase": "Last Quarter", "moon_illumination": "41"}], "maxtempC": "32", "maxtempF": "90", "mintempC": "23", "mintempF": "73", "avgtempC": "29", "avgtempF": "84", "totalSnow_cm": "0.0", "sunHour": "11.6", "uvIndex": "6", "hourly": [{"time": "24", "tempC": "32", "tempF": "90", "windspeedMiles": "13", "windspeedKmph": "21", "winddirDegree": "158", "winddir16Point": "SSE", "weatherCode": "200", "weatherIconUrl": [{"value": "http://cdn.worldweatheronline.com/images/wsymbols01_png_64/wsymbol_0016_thundery_showers.png"}], "weatherDesc": [{"value": "Thundery outbreaks possible"}], "precipMM": "3.2", "precipInches": "0.1", "humidity": "66", "visibility": "10", "visibilityMiles": "5", "pressure": "1012", "pressureInches": "30", "cloudcover": "23", "HeatIndexC": "30", "HeatIndexF": "85", "DewPointC": "20", "DewPointF": "68", "WindChillC": "27", "WindChillF": "81", "WindGustMiles": "18", "WindGustKmph": "30", "FeelsLikeC": "30", "FeelsLikeF": "85", "uvIndex": "6"}]}, {"date": "2018-09-03", "astronomy": [{"sunrise": "07:03 AM", "sunset": "07:58 PM", "moonrise": "12:29 AM", "moonset": "03:03 PM", "moon_phase": "Last Quarter", "moon_illumination": "33"}], "maxtempC": "29", "maxtempF": "83", "mintempC": "21", "mintempF": "71", "avgtempC": "25", "avgtempF": "78", "totalSnow_cm": "0.0", "sunHour": "7.6", "uvIndex": "6", "hourly": [{"time": "24", "tempC": "29", "tempF": "83", "windspeedMiles": "10", "windspeedKmph": "16", "winddirDegree": "156", "winddir16Point": "SSE", "weatherCode": "122", "weatherIconUrl": [{"value": "http://cdn.worldweatheronline.com/images/wsymbols01_png_64/wsymbol_0004_black_low_cloud.png"}], "weatherDesc": [{"value": "Overcast"}], "precipMM": "4.1", "precipInches": "0.2", "humidity": "81", "visibility": "10", "visibilityMiles": "5", "pressure": "1015", "pressureInches": "30", "cloudcover": "67", "HeatIndexC": "27", "HeatIndexF": "80", "DewPointC": "21", "DewPointF": "70", "WindChillC": "25", "WindChillF": "76", "WindGustMiles": "14", "WindGustKmph": "23", "FeelsLikeC": "27", "FeelsLikeF": "80", "uvIndex": "6"}]}, {"date": "2018-09-04", "astronomy": [{"sunrise": "07:04 AM", "sunset": "07:56 PM", "moonrise": "01:19 AM", "moonset": "04:06 PM", "moon_phase": "Last Quarter", "moon_illumination": "26"}], "maxtempC": "29", "maxtempF": "83", "mintempC": "22", "mintempF": "72", "avgtempC": "26", "avgtempF": "78", "totalSnow_cm": "0.0", "sunHour": "10.3", "uvIndex": "6", "hourly": [{"time": "24", "tempC": "29", "tempF": "83", "windspeedMiles": "12", "windspeedKmph": "19", "winddirDegree": "168", "winddir16Point": "SSE", "weatherCode": "356", "weatherIconUrl": [{"value": "http://cdn.worldweatheronline.com/images/wsymbols01_png_64/wsymbol_0010_heavy_rain_showers.png"}], "weatherDesc": [{"value": "Moderate or heavy rain shower"}], "precipMM": "6.1", "precipInches": "0.2", "humidity": "81", "visibility": "10", "visibilityMiles": "5", "pressure": "1014", "pressureInches": "30", "cloudcover": "79", "HeatIndexC": "27", "HeatIndexF": "80", "DewPointC": "21", "DewPointF": "70", "WindChillC": "25", "WindChillF": "76", "WindGustMiles": "16", "WindGustKmph": "26", "FeelsLikeC": "27", "FeelsLikeF": "80", "uvIndex": "6"}]}, {"date": "2018-09-05", "astronomy": [{"sunrise": "07:05 AM", "sunset": "07:55 PM", "moonrise": "02:15 AM", "moonset": "05:05 PM", "moon_phase": "Waning Crescent", "moon_illumination": "18"}], "maxtempC": "30", "maxtempF": "85", "mintempC": "21", "mintempF": "70", "avgtempC": "26", "avgtempF": "78", "totalSnow_cm": "0.0", "sunHour": "11.6", "uvIndex": "6", "hourly": [{"time": "24", "tempC": "30", "tempF": "85", "windspeedMiles": "6", "windspeedKmph": "10", "winddirDegree": "165", "winddir16Point": "SSE", "weatherCode": "353", "weatherIconUrl": [{"value": "http://cdn.worldweatheronline.com/images/wsymbols01_png_64/wsymbol_0009_light_rain_showers.png"}], "weatherDesc": [{"value": "Light rain shower"}], "precipMM": "9.0", "precipInches": "0.4", "humidity": "78", "visibility": "9", "visibilityMiles": "5", "pressure": "1017", "pressureInches": "31", "cloudcover": "45", "HeatIndexC": "27", "HeatIndexF": "80", "DewPointC": "20", "DewPointF": "68", "WindChillC": "25", "WindChillF": "76", "WindGustMiles": "9", "WindGustKmph": "15", "FeelsLikeC": "27", "FeelsLikeF": "80", "uvIndex": "6"}]}, {"date": "2018-09-06", "astronomy": [{"sunrise": "07:06 AM", "sunset": "07:53 PM", "moonrise": "03:19 AM", "moonset": "06:00 PM", "moon_phase": "Waning Crescent", "moon_illumination": "11"}], "maxtempC": "24", "maxtempF": "75", "mintempC": "20", "mintempF": "68", "avgtempC": "22", "avgtempF": "72", "totalSnow_cm": "0.0", "sunHour": "6.2", "uvIndex": "5", "hourly": [{"time": "24", "tempC": "24", "tempF": "75", "windspeedMiles": "11", "windspeedKmph": "18", "winddirDegree": "21", "winddir16Point": "NNE", "weatherCode": "353", "weatherIconUrl": [{"value": "http://cdn.worldweatheronline.com/images/wsymbols01_png_64/wsymbol_0009_light_rain_showers.png"}], "weatherDesc": [{"value": "Light rain shower"}], "precipMM": "2.2", "precipInches": "0.1", "humidity": "87", "visibility": "9", "visibilityMiles": "5", "pressure": "1020", "pressureInches": "31", "cloudcover": "98", "HeatIndexC": "23", "HeatIndexF": "74", "DewPointC": "19", "DewPointF": "67", "WindChillC": "22", "WindChillF": "71", "WindGustMiles": "15", "WindGustKmph": "23", "FeelsLikeC": "23", "FeelsLikeF": "74", "uvIndex": "5"}]}, {"date": "2018-09-07", "astronomy": [{"sunrise": "07:07 AM", "sunset": "07:52 PM", "moonrise": "04:27 AM", "moonset": "06:48 PM", "moon_phase": "Waning Crescent", "moon_illumination": "3"}], "maxtempC": "24", "maxtempF": "75", "mintempC": "19", "mintempF": "67", "avgtempC": "22", "avgtempF": "72", "totalSnow_cm": "0.0", "sunHour": "6.2", "uvIndex": "5", "hourly": [{"time": "24", "tempC": "24", "tempF": "75", "windspeedMiles": "9", "windspeedKmph": "14", "winddirDegree": "24", "winddir16Point": "NNE", "weatherCode": "356", "weatherIconUrl": [{"value": "http://cdn.worldweatheronline.com/images/wsymbols01_png_64/wsymbol_0010_heavy_rain_showers.png"}], "weatherDesc": [{"value": "Moderate or heavy rain shower"}], "precipMM": "14.6", "precipInches": "0.6", "humidity": "89", "visibility": "9", "visibilityMiles": "5", "pressure": "1019", "pressureInches": "31", "cloudcover": "97", "HeatIndexC": "22", "HeatIndexF": "72", "DewPointC": "19", "DewPointF": "67", "WindChillC": "21", "WindChillF": "70", "WindGustMiles": "12", "WindGustKmph": "20", "FeelsLikeC": "22", "FeelsLikeF": "72", "uvIndex": "5"}]}, {"date": "2018-09-08", "astronomy": [{"sunrise": "07:08 AM", "sunset": "07:50 PM", "moonrise": "05:40 AM", "moonset": "07:32 PM", "moon_phase": "New Moon", "moon_illumination": "0"}], "maxtempC": "21", "maxtempF": "69", "mintempC": "18", "mintempF": "65", "avgtempC": "20", "avgtempF": "67", "totalSnow_cm": "0.0", "sunHour": "6.2", "uvIndex": "4", "hourly": [{"time": "24", "tempC": "21", "tempF": "69", "windspeedMiles": "11", "windspeedKmph": "17", "winddirDegree": "30", "winddir16Point": "NNE", "weatherCode": "353", "weatherIconUrl": [{"value": "http://cdn.worldweatheronline.com/images/wsymbols01_png_64/wsymbol_0009_light_rain_showers.png"}], "weatherDesc": [{"value": "Light rain shower"}], "precipMM": "3.1", "precipInches": "0.1", "humidity": "86", "visibility": "9", "visibilityMiles": "5", "pressure": "1017", "pressureInches": "31", "cloudcover": "98", "HeatIndexC": "20", "HeatIndexF": "67", "DewPointC": "17", "DewPointF": "63", "WindChillC": "20", "WindChillF": "67", "WindGustMiles": "14", "WindGustKmph": "22", "FeelsLikeC": "20", "FeelsLikeF": "67", "uvIndex": "4"}]}, {"date": "2018-09-09", "astronomy": [{"sunrise": "07:08 AM", "sunset": "07:49 PM", "moonrise": "06:51 AM", "moonset": "08:10 PM", "moon_phase": "New Moon", "moon_illumination": "0"}], "maxtempC": "25", "maxtempF": "76", "mintempC": "14", "mintempF": "57", "avgtempC": "21", "avgtempF": "69", "totalSnow_cm": "0.0", "sunHour": "11.6", "uvIndex": "6", "hourly": [{"time": "24", "tempC": "25", "tempF": "76", "windspeedMiles": "7", "windspeedKmph": "11", "winddirDegree": "63", "winddir16Point": "ENE", "weatherCode": "113", "weatherIconUrl": [{"value": "http://cdn.worldweatheronline.com/images/wsymbols01_png_64/wsymbol_0001_sunny.png"}], "weatherDesc": [{"value": "Sunny"}], "precipMM": "0.0", "precipInches": "0.0", "humidity": "71", "visibility": "10", "visibilityMiles": "6", "pressure": "1016", "pressureInches": "30", "cloudcover": "10", "HeatIndexC": "20", "HeatIndexF": "67", "DewPointC": "13", "DewPointF": "56", "WindChillC": "19", "WindChillF": "66", "WindGustMiles": "10", "WindGustKmph": "16", "FeelsLikeC": "19", "FeelsLikeF": "66", "uvIndex": "6"}]}, {"date": "2018-09-10", "astronomy": [{"sunrise": "07:09 AM", "sunset": "07:47 PM", "moonrise": "08:02 AM", "moonset": "08:46 PM", "moon_phase": "New Moon", "moon_illumination": "0"}], "maxtempC": "25", "maxtempF": "76", "mintempC": "14", "mintempF": "57", "avgtempC": "21", "avgtempF": "69", "totalSnow_cm": "0.0", "sunHour": "11.6", "uvIndex": "6", "hourly": [{"time": "24", "tempC": "25", "tempF": "76", "windspeedMiles": "6", "windspeedKmph": "10", "winddirDegree": "150", "winddir16Point": "SSE", "weatherCode": "113", "weatherIconUrl": [{"value": "http://cdn.worldweatheronline.com/images/wsymbols01_png_64/wsymbol_0001_sunny.png"}], "weatherDesc": [{"value": "Sunny"}], "precipMM": "0.0", "precipInches": "0.0", "humidity": "76", "visibility": "10", "visibilityMiles": "6", "pressure": "1016", "pressureInches": "30", "cloudcover": "8", "HeatIndexC": "20", "HeatIndexF": "67", "DewPointC": "14", "DewPointF": "57", "WindChillC": "19", "WindChillF": "66", "WindGustMiles": "9", "WindGustKmph": "15", "FeelsLikeC": "19", "FeelsLikeF": "66", "uvIndex": "6"}]}, {"date": "2018-09-11", "astronomy": [{"sunrise": "07:10 AM", "sunset": "07:46 PM", "moonrise": "09:11 AM", "moonset": "09:20 PM", "moon_phase": "Waxing Crescent", "moon_illumination": "4"}], "maxtempC": "27", "maxtempF": "80", "mintempC": "16", "mintempF": "61", "avgtempC": "23", "avgtempF": "73", "totalSnow_cm": "0.0", "sunHour": "10.2", "uvIndex": "6", "hourly": [{"time": "24", "tempC": "27", "tempF": "80", "windspeedMiles": "10", "windspeedKmph": "17", "winddirDegree": "166", "winddir16Point": "SSE", "weatherCode": "116", "weatherIconUrl": [{"value": "http://cdn.worldweatheronline.com/images/wsymbols01_png_64/wsymbol_0002_sunny_intervals.png"}], "weatherDesc": [{"value": "Partly cloudy"}], "precipMM": "0.0", "precipInches": "0.0", "humidity": "76", "visibility": "10", "visibilityMiles": "6", "pressure": "1016", "pressureInches": "30", "cloudcover": "22", "HeatIndexC": "22", "HeatIndexF": "71", "DewPointC": "16", "DewPointF": "61", "WindChillC": "21", "WindChillF": "70", "WindGustMiles": "16", "WindGustKmph": "25", "FeelsLikeC": "22", "FeelsLikeF": "71", "uvIndex": "6"}]}, {"date": "2018-09-12", "astronomy": [{"sunrise": "07:11 AM", "sunset": "07:44 PM", "moonrise": "10:17 AM", "moonset": "09:54 PM", "moon_phase": "Waxing Crescent", "moon_illumination": "12"}], "maxtempC": "27", "maxtempF": "80", "mintempC": "17", "mintempF": "62", "avgtempC": "23", "avgtempF": "73", "totalSnow_cm": "0.0", "sunHour": "10.2", "uvIndex": "5", "hourly": [{"time": "24", "tempC": "27", "tempF": "80", "windspeedMiles": "12", "windspeedKmph": "19", "winddirDegree": "163", "winddir16Point": "SSE", "weatherCode": "119", "weatherIconUrl": [{"value": "http://cdn.worldweatheronline.com/images/wsymbols01_png_64/wsymbol_0003_white_cloud.png"}], "weatherDesc": [{"value": "Cloudy"}], "precipMM": "0.1", "precipInches": "0.0", "humidity": "79", "visibility": "10", "visibilityMiles": "6", "pressure": "1015", "pressureInches": "30", "cloudcover": "36", "HeatIndexC": "23", "HeatIndexF": "73", "DewPointC": "18", "DewPointF": "64", "WindChillC": "22", "WindChillF": "71", "WindGustMiles": "18", "WindGustKmph": "29", "FeelsLikeC": "23", "FeelsLikeF": "73", "uvIndex": "5"}]}, {"date": "2018-09-13", "astronomy": [{"sunrise": "07:12 AM", "sunset": "07:42 PM", "moonrise": "11:22 AM", "moonset": "10:29 PM", "moon_phase": "Waxing Crescent", "moon_illumination": "19"}], "maxtempC": "29", "maxtempF": "84", "mintempC": "20", "mintempF": "69", "avgtempC": "25", "avgtempF": "78", "totalSnow_cm": "0.0", "sunHour": "10.2", "uvIndex": "6", "hourly": [{"time": "24", "tempC": "29", "tempF": "84", "windspeedMiles": "15", "windspeedKmph": "25", "winddirDegree": "174", "winddir16Point": "S", "weatherCode": "122", "weatherIconUrl": [{"value": "http://cdn.worldweatheronline.com/images/wsymbols01_png_64/wsymbol_0004_black_low_cloud.png"}], "weatherDesc": [{"value": "Overcast"}], "precipMM": "0.1", "precipInches": "0.0", "humidity": "79", "visibility": "10", "visibilityMiles": "6", "pressure": "1015", "pressureInches": "30", "cloudcover": "40", "HeatIndexC": "26", "HeatIndexF": "79", "DewPointC": "20", "DewPointF": "68", "WindChillC": "24", "WindChillF": "75", "WindGustMiles": "22", "WindGustKmph": "35", "FeelsLikeC": "26", "FeelsLikeF": "79", "uvIndex": "6"}]}, {"date": "2018-09-14", "astronomy": [{"sunrise": "07:13 AM", "sunset": "07:41 PM", "moonrise": "12:23 PM", "moonset": "11:06 PM", "moon_phase": "Waxing Crescent", "moon_illumination": "27"}], "maxtempC": "31", "maxtempF": "89", "mintempC": "21", "mintempF": "70", "avgtempC": "28", "avgtempF": "82", "totalSnow_cm": "0.0", "sunHour": "11.6", "uvIndex": "7", "hourly": [{"time": "24", "tempC": "31", "tempF": "89", "windspeedMiles": "13", "windspeedKmph": "21", "winddirDegree": "176", "winddir16Point": "S", "weatherCode": "116", "weatherIconUrl": [{"value": "http://cdn.worldweatheronline.com/images/wsymbols01_png_64/wsymbol_0002_sunny_intervals.png"}], "weatherDesc": [{"value": "Partly cloudy"}], "precipMM": "0.0", "precipInches": "0.0", "humidity": "72", "visibility": "10", "visibilityMiles": "6", "pressure": "1016", "pressureInches": "30", "cloudcover": "12", "HeatIndexC": "28", "HeatIndexF": "83", "DewPointC": "20", "DewPointF": "68", "WindChillC": "26", "WindChillF": "79", "WindGustMiles": "19", "WindGustKmph": "31", "FeelsLikeC": "28", "FeelsLikeF": "83", "uvIndex": "7"}]}, {"date": "2018-09-15", "astronomy": [{"sunrise": "07:13 AM", "sunset": "07:39 PM", "moonrise": "01:24 PM", "moonset": "11:45 PM", "moon_phase": "Waxing Crescent", "moon_illumination": "34"}], "maxtempC": "31", "maxtempF": "88", "mintempC": "22", "mintempF": "71", "avgtempC": "28", "avgtempF": "82", "totalSnow_cm": "0.0", "sunHour": "11.6", "uvIndex": "6", "hourly": [{"time": "24", "tempC": "31", "tempF": "88", "windspeedMiles": "6", "windspeedKmph": "10", "winddirDegree": "166", "winddir16Point": "SSE", "weatherCode": "176", "weatherIconUrl": [{"value": "http://cdn.worldweatheronline.com/images/wsymbols01_png_64/wsymbol_0009_light_rain_showers.png"}], "weatherDesc": [{"value": "Patchy rain possible"}], "precipMM": "0.7", "precipInches": "0.0", "humidity": "67", "visibility": "10", "visibilityMiles": "6", "pressure": "1017", "pressureInches": "31", "cloudcover": "22", "HeatIndexC": "28", "HeatIndexF": "82", "DewPointC": "19", "DewPointF": "66", "WindChillC": "26", "WindChillF": "79", "WindGustMiles": "10", "WindGustKmph": "17", "FeelsLikeC": "28", "FeelsLikeF": "82", "uvIndex": "6"}]}, {"date": "2018-09-16", "astronomy": [{"sunrise": "07:14 AM", "sunset": "07:38 PM", "moonrise": "02:20 PM", "moonset": "No moonset", "moon_phase": "First Quarter", "moon_illumination": "42"}], "maxtempC": "31", "maxtempF": "88", "mintempC": "22", "mintempF": "71", "avgtempC": "28", "avgtempF": "82", "totalSnow_cm": "0.0", "sunHour": "11.6", "uvIndex": "7", "hourly": [{"time": "24", "tempC": "31", "tempF": "88", "windspeedMiles": "6", "windspeedKmph": "9", "winddirDegree": "163", "winddir16Point": "SSE", "weatherCode": "116", "weatherIconUrl": [{"value": "http://cdn.worldweatheronline.com/images/wsymbols01_png_64/wsymbol_0002_sunny_intervals.png"}], "weatherDesc": [{"value": "Partly cloudy"}], "precipMM": "1.1", "precipInches": "0.0", "humidity": "66", "visibility": "10", "visibilityMiles": "6", "pressure": "1015", "pressureInches": "30", "cloudcover": "39", "HeatIndexC": "28", "HeatIndexF": "82", "DewPointC": "19", "DewPointF": "66", "WindChillC": "26", "WindChillF": "79", "WindGustMiles": "9", "WindGustKmph": "14", "FeelsLikeC": "28", "FeelsLikeF": "82", "uvIndex": "7"}]}, {"date": "2018-09-17", "astronomy": [{"sunrise": "07:15 AM", "sunset": "07:36 PM", "moonrise": "03:13 PM", "moonset": "12:27 AM", "moon_phase": "First Quarter", "moon_illumination": "49"}], "maxtempC": "33", "maxtempF": "91", "mintempC": "22", "mintempF": "72", "avgtempC": "29", "avgtempF": "84", "totalSnow_cm": "0.0", "sunHour": "11.6", "uvIndex": "6", "hourly": [{"time": "24", "tempC": "33", "tempF": "91", "windspeedMiles": "10", "windspeedKmph": "16", "winddirDegree": "184", "winddir16Point": "S", "weatherCode": "176", "weatherIconUrl": [{"value": "http://cdn.worldweatheronline.com/images/wsymbols01_png_64/wsymbol_0009_light_rain_showers.png"}], "weatherDesc": [{"value": "Patchy rain possible"}], "precipMM": "3.4", "precipInches": "0.1", "humidity": "67", "visibility": "10", "visibilityMiles": "5", "pressure": "1013", "pressureInches": "30", "cloudcover": "23", "HeatIndexC": "29", "HeatIndexF": "85", "DewPointC": "20", "DewPointF": "68", "WindChillC": "27", "WindChillF": "81", "WindGustMiles": "16", "WindGustKmph": "25", "FeelsLikeC": "29", "FeelsLikeF": "85", "uvIndex": "6"}]}, {"date": "2018-09-18", "astronomy": [{"sunrise": "07:16 AM", "sunset": "07:35 PM", "moonrise": "04:02 PM", "moonset": "01:14 AM", "moon_phase": "First Quarter", "moon_illumination": "57"}], "maxtempC": "33", "maxtempF": "91", "mintempC": "23", "mintempF": "73", "avgtempC": "29", "avgtempF": "85", "totalSnow_cm": "0.0", "sunHour": "11.6", "uvIndex": "7", "hourly": [{"time": "24", "tempC": "33", "tempF": "91", "windspeedMiles": "12", "windspeedKmph": "19", "winddirDegree": "188", "winddir16Point": "S", "weatherCode": "116", "weatherIconUrl": [{"value": "http://cdn.worldweatheronline.com/images/wsymbols01_png_64/wsymbol_0002_sunny_intervals.png"}], "weatherDesc": [{"value": "Partly cloudy"}], "precipMM": "0.3", "precipInches": "0.0", "humidity": "63", "visibility": "10", "visibilityMiles": "6", "pressure": "1011", "pressureInches": "30", "cloudcover": "16", "HeatIndexC": "30", "HeatIndexF": "86", "DewPointC": "20", "DewPointF": "68", "WindChillC": "28", "WindChillF": "82", "WindGustMiles": "18", "WindGustKmph": "29", "FeelsLikeC": "30", "FeelsLikeF": "86", "uvIndex": "7"}]}, {"date": "2018-09-19", "astronomy": [{"sunrise": "07:17 AM", "sunset": "07:33 PM", "moonrise": "04:46 PM", "moonset": "02:04 AM", "moon_phase": "First Quarter", "moon_illumination": "64"}], "maxtempC": "33", "maxtempF": "92", "mintempC": "24", "mintempF": "76", "avgtempC": "30", "avgtempF": "85", "totalSnow_cm": "0.0", "sunHour": "11.6", "uvIndex": "7", "hourly": [{"time": "24", "tempC": "33", "tempF": "92", "windspeedMiles": "15", "windspeedKmph": "24", "winddirDegree": "187", "winddir16Point": "S", "weatherCode": "113", "weatherIconUrl": [{"value": "http://cdn.worldweatheronline.com/images/wsymbols01_png_64/wsymbol_0001_sunny.png"}], "weatherDesc": [{"value": "Sunny"}], "precipMM": "0.0", "precipInches": "0.0", "humidity": "55", "visibility": "10", "visibilityMiles": "6", "pressure": "1010", "pressureInches": "30", "cloudcover": "13", "HeatIndexC": "30", "HeatIndexF": "86", "DewPointC": "18", "DewPointF": "65", "WindChillC": "28", "WindChillF": "83", "WindGustMiles": "22", "WindGustKmph": "36", "FeelsLikeC": "30", "FeelsLikeF": "86", "uvIndex": "7"}]}, {"date": "2018-09-20", "astronomy": [{"sunrise": "07:18 AM", "sunset": "07:32 PM", "moonrise": "05:26 PM", "moonset": "02:56 AM", "moon_phase": "Waxing Gibbous", "moon_illumination": "72"}], "maxtempC": "33", "maxtempF": "92", "mintempC": "25", "mintempF": "76", "avgtempC": "29", "avgtempF": "85", "totalSnow_cm": "0.0", "sunHour": "11.6", "uvIndex": "7", "hourly": [{"time": "24", "tempC": "33", "tempF": "92", "windspeedMiles": "18", "windspeedKmph": "29", "winddirDegree": "192", "winddir16Point": "SSW", "weatherCode": "113", "weatherIconUrl": [{"value": "http://cdn.worldweatheronline.com/images/wsymbols01_png_64/wsymbol_0001_sunny.png"}], "weatherDesc": [{"value": "Sunny"}], "precipMM": "2.4", "precipInches": "0.1", "humidity": "54", "visibility": "10", "visibilityMiles": "6", "pressure": "1009", "pressureInches": "30", "cloudcover": "7", "HeatIndexC": "29", "HeatIndexF": "85", "DewPointC": "18", "DewPointF": "64", "WindChillC": "28", "WindChillF": "83", "WindGustMiles": "26", "WindGustKmph": "42", "FeelsLikeC": "29", "FeelsLikeF": "85", "uvIndex": "7"}]}, {"date": "2018-09-21", "astronomy": [{"sunrise": "07:19 AM", "sunset": "07:30 PM", "moonrise": "06:02 PM", "moonset": "03:52 AM", "moon_phase": "Waxing Gibbous", "moon_illumination": "80"}], "maxtempC": "20", "maxtempF": "68", "mintempC": "15", "mintempF": "60", "avgtempC": "19", "avgtempF": "66", "totalSnow_cm": "0.0", "sunHour": "10.2", "uvIndex": "4", "hourly": [{"time": "24", "tempC": "20", "tempF": "68", "windspeedMiles": "10", "windspeedKmph": "16", "winddirDegree": "74", "winddir16Point": "ENE", "weatherCode": "359", "weatherIconUrl": [{"value": "http://cdn.worldweatheronline.com/images/wsymbols01_png_64/wsymbol_0018_cloudy_with_heavy_rain.png"}], "weatherDesc": [{"value": "Torrential rain shower"}], "precipMM": "16.3", "precipInches": "0.6", "humidity": "68", "visibility": "9", "visibilityMiles": "5", "pressure": "1019", "pressureInches": "31", "cloudcover": "48", "HeatIndexC": "20", "HeatIndexF": "68", "DewPointC": "13", "DewPointF": "56", "WindChillC": "20", "WindChillF": "67", "WindGustMiles": "14", "WindGustKmph": "23", "FeelsLikeC": "20", "FeelsLikeF": "67", "uvIndex": "4"}]}, {"date": "2018-09-22", "astronomy": [{"sunrise": "07:19 AM", "sunset": "07:28 PM", "moonrise": "06:36 PM", "moonset": "04:48 AM", "moon_phase": "Waxing Gibbous", "moon_illumination": "87"}], "maxtempC": "23", "maxtempF": "74", "mintempC": "11", "mintempF": "52", "avgtempC": "18", "avgtempF": "65", "totalSnow_cm": "0.0", "sunHour": "11.6", "uvIndex": "5", "hourly": [{"time": "24", "tempC": "23", "tempF": "74", "windspeedMiles": "9", "windspeedKmph": "14", "winddirDegree": "63", "winddir16Point": "ENE", "weatherCode": "113", "weatherIconUrl": [{"value": "http://cdn.worldweatheronline.com/images/wsymbols01_png_64/wsymbol_0001_sunny.png"}], "weatherDesc": [{"value": "Sunny"}], "precipMM": "0.0", "precipInches": "0.0", "humidity": "66", "visibility": "10", "visibilityMiles": "6", "pressure": "1022", "pressureInches": "31", "cloudcover": "1", "HeatIndexC": "17", "HeatIndexF": "62", "DewPointC": "10", "DewPointF": "50", "WindChillC": "16", "WindChillF": "61", "WindGustMiles": "14", "WindGustKmph": "22", "FeelsLikeC": "16", "FeelsLikeF": "61", "uvIndex": "5"}]}, {"date": "2018-09-23", "astronomy": [{"sunrise": "07:20 AM", "sunset": "07:27 PM", "moonrise": "07:07 PM", "moonset": "05:46 AM", "moon_phase": "Waxing Gibbous", "moon_illumination": "95"}], "maxtempC": "25", "maxtempF": "78", "mintempC": "14", "mintempF": "56", "avgtempC": "21", "avgtempF": "69", "totalSnow_cm": "0.0", "sunHour": "11.6", "uvIndex": "5", "hourly": [{"time": "24", "tempC": "25", "tempF": "78", "windspeedMiles": "7", "windspeedKmph": "11", "winddirDegree": "140", "winddir16Point": "SE", "weatherCode": "143", "weatherIconUrl": [{"value": "http://cdn.worldweatheronline.com/images/wsymbols01_png_64/wsymbol_0006_mist.png"}], "weatherDesc": [{"value": "Mist"}], "precipMM": "0.0", "precipInches": "0.0", "humidity": "76", "visibility": "8", "visibilityMiles": "4", "pressure": "1016", "pressureInches": "30", "cloudcover": "14", "HeatIndexC": "19", "HeatIndexF": "67", "DewPointC": "14", "DewPointF": "57", "WindChillC": "19", "WindChillF": "66", "WindGustMiles": "11", "WindGustKmph": "17", "FeelsLikeC": "19", "FeelsLikeF": "66", "uvIndex": "5"}]}, {"date": "2018-09-24", "astronomy": [{"sunrise": "07:21 AM", "sunset": "07:25 PM", "moonrise": "07:38 PM", "moonset": "06:43 AM", "moon_phase": "Full Moon", "moon_illumination": "100"}], "maxtempC": "27", "maxtempF": "80", "mintempC": "17", "mintempF": "62", "avgtempC": "22", "avgtempF": "72", "totalSnow_cm": "0.0", "sunHour": "11.6", "uvIndex": "6", "hourly": [{"time": "24", "tempC": "27", "tempF": "80", "windspeedMiles": "11", "windspeedKmph": "18", "winddirDegree": "177", "winddir16Point": "S", "weatherCode": "116", "weatherIconUrl": [{"value": "http://cdn.worldweatheronline.com/images/wsymbols01_png_64/wsymbol_0002_sunny_intervals.png"}], "weatherDesc": [{"value": "Partly cloudy"}], "precipMM": "0.0", "precipInches": "0.0", "humidity": "81", "visibility": "10", "visibilityMiles": "6", "pressure": "1011", "pressureInches": "30", "cloudcover": "32", "HeatIndexC": "21", "HeatIndexF": "70", "DewPointC": "17", "DewPointF": "63", "WindChillC": "21", "WindChillF": "70", "WindGustMiles": "16", "WindGustKmph": "26", "FeelsLikeC": "21", "FeelsLikeF": "70", "uvIndex": "6"}]}, {"date": "2018-09-25", "astronomy": [{"sunrise": "07:22 AM", "sunset": "07:24 PM", "moonrise": "08:07 PM", "moonset": "07:43 AM", "moon_phase": "Full Moon", "moon_illumination": "100"}], "maxtempC": "23", "maxtempF": "73", "mintempC": "16", "mintempF": "61", "avgtempC": "21", "avgtempF": "69", "totalSnow_cm": "0.0", "sunHour": "10.2", "uvIndex": "5", "hourly": [{"time": "24", "tempC": "23", "tempF": "73", "windspeedMiles": "15", "windspeedKmph": "24", "winddirDegree": "136", "winddir16Point": "SE", "weatherCode": "119", "weatherIconUrl": [{"value": "http://cdn.worldweatheronline.com/images/wsymbols01_png_64/wsymbol_0003_white_cloud.png"}], "weatherDesc": [{"value": "Cloudy"}], "precipMM": "0.0", "precipInches": "0.0", "humidity": "75", "visibility": "10", "visibilityMiles": "6", "pressure": "1013", "pressureInches": "30", "cloudcover": "45", "HeatIndexC": "21", "HeatIndexF": "69", "DewPointC": "15", "DewPointF": "59", "WindChillC": "20", "WindChillF": "68", "WindGustMiles": "21", "WindGustKmph": "33", "FeelsLikeC": "20", "FeelsLikeF": "68", "uvIndex": "5"}]}, {"date": "2018-09-26", "astronomy": [{"sunrise": "07:23 AM", "sunset": "07:22 PM", "moonrise": "08:38 PM", "moonset": "08:43 AM", "moon_phase": "Waxing Gibbous", "moon_illumination": "83"}], "maxtempC": "20", "maxtempF": "68", "mintempC": "13", "mintempF": "55", "avgtempC": "16", "avgtempF": "61", "totalSnow_cm": "0.0", "sunHour": "8.8", "uvIndex": "4", "hourly": [{"time": "24", "tempC": "20", "tempF": "68", "windspeedMiles": "7", "windspeedKmph": "12", "winddirDegree": "59", "winddir16Point": "ENE", "weatherCode": "119", "weatherIconUrl": [{"value": "http://cdn.worldweatheronline.com/images/wsymbols01_png_64/wsymbol_0003_white_cloud.png"}], "weatherDesc": [{"value": "Cloudy"}], "precipMM": "0.1", "precipInches": "0.0", "humidity": "53", "visibility": "10", "visibilityMiles": "6", "pressure": "1024", "pressureInches": "31", "cloudcover": "31", "HeatIndexC": "15", "HeatIndexF": "59", "DewPointC": "5", "DewPointF": "42", "WindChillC": "14", "WindChillF": "58", "WindGustMiles": "12", "WindGustKmph": "19", "FeelsLikeC": "14", "FeelsLikeF": "58", "uvIndex": "4"}]}, {"date": "2018-09-27", "astronomy": [{"sunrise": "07:24 AM", "sunset": "07:21 PM", "moonrise": "09:11 PM", "moonset": "09:45 AM", "moon_phase": "Waning Gibbous", "moon_illumination": "75"}], "maxtempC": "23", "maxtempF": "74", "mintempC": "10", "mintempF": "51", "avgtempC": "18", "avgtempF": "64", "totalSnow_cm": "0.0", "sunHour": "11.6", "uvIndex": "5", "hourly": [{"time": "24", "tempC": "23", "tempF": "74", "windspeedMiles": "9", "windspeedKmph": "14", "winddirDegree": "194", "winddir16Point": "SSW", "weatherCode": "113", "weatherIconUrl": [{"value": "http://cdn.worldweatheronline.com/images/wsymbols01_png_64/wsymbol_0001_sunny.png"}], "weatherDesc": [{"value": "Sunny"}], "precipMM": "0.0", "precipInches": "0.0", "humidity": "54", "visibility": "10", "visibilityMiles": "6", "pressure": "1017", "pressureInches": "31", "cloudcover": "3", "HeatIndexC": "17", "HeatIndexF": "62", "DewPointC": "7", "DewPointF": "44", "WindChillC": "16", "WindChillF": "60", "WindGustMiles": "14", "WindGustKmph": "23", "FeelsLikeC": "16", "FeelsLikeF": "60", "uvIndex": "5"}]}, {"date": "2018-09-28", "astronomy": [{"sunrise": "07:25 AM", "sunset": "07:19 PM", "moonrise": "09:47 PM", "moonset": "10:48 AM", "moon_phase": "Waning Gibbous", "moon_illumination": "68"}], "maxtempC": "18", "maxtempF": "64", "mintempC": "12", "mintempF": "53", "avgtempC": "16", "avgtempF": "61", "totalSnow_cm": "0.0", "sunHour": "6.0", "uvIndex": "4", "hourly": [{"time": "24", "tempC": "18", "tempF": "64", "windspeedMiles": "11", "windspeedKmph": "17", "winddirDegree": "96", "winddir16Point": "E", "weatherCode": "122", "weatherIconUrl": [{"value": "http://cdn.worldweatheronline.com/images/wsymbols01_png_64/wsymbol_0004_black_low_cloud.png"}], "weatherDesc": [{"value": "Overcast"}], "precipMM": "0.7", "precipInches": "0.0", "humidity": "69", "visibility": "9", "visibilityMiles": "5", "pressure": "1019", "pressureInches": "31", "cloudcover": "58", "HeatIndexC": "15", "HeatIndexF": "59", "DewPointC": "10", "DewPointF": "49", "WindChillC": "15", "WindChillF": "58", "WindGustMiles": "16", "WindGustKmph": "26", "FeelsLikeC": "15", "FeelsLikeF": "58", "uvIndex": "4"}]}, {"date": "2018-09-29", "astronomy": [{"sunrise": "07:26 AM", "sunset": "07:18 PM", "moonrise": "10:28 PM", "moonset": "11:52 AM", "moon_phase": "Waning Gibbous", "moon_illumination": "60"}], "maxtempC": "21", "maxtempF": "69", "mintempC": "10", "mintempF": "50", "avgtempC": "16", "avgtempF": "61", "totalSnow_cm": "0.0", "sunHour": "7.4", "uvIndex": "4", "hourly": [{"time": "24", "tempC": "21", "tempF": "69", "windspeedMiles": "11", "windspeedKmph": "18", "winddirDegree": "133", "winddir16Point": "SE", "weatherCode": "296", "weatherIconUrl": [{"value": "http://cdn.worldweatheronline.com/images/wsymbols01_png_64/wsymbol_0017_cloudy_with_light_rain.png"}], "weatherDesc": [{"value": "Light rain"}], "precipMM": "4.4", "precipInches": "0.2", "humidity": "85", "visibility": "10", "visibilityMiles": "5", "pressure": "1020", "pressureInches": "31", "cloudcover": "84", "HeatIndexC": "15", "HeatIndexF": "60", "DewPointC": "13", "DewPointF": "55", "WindChillC": "14", "WindChillF": "58", "WindGustMiles": "16", "WindGustKmph": "25", "FeelsLikeC": "14", "FeelsLikeF": "58", "uvIndex": "4"}]}, {"date": "2018-09-30", "astronomy": [{"sunrise": "07:26 AM", "sunset": "07:16 PM", "moonrise": "11:14 PM", "moonset": "12:56 PM", "moon_phase": "Waning Gibbous", "moon_illumination": "52"}], "maxtempC": "28", "maxtempF": "83", "mintempC": "20", "mintempF": "67", "avgtempC": "24", "avgtempF": "75", "totalSnow_cm": "0.0", "sunHour": "8.8", "uvIndex": "5", "hourly": [{"time": "24", "tempC": "28", "tempF": "83", "windspeedMiles": "16", "windspeedKmph": "26", "winddirDegree": "176", "winddir16Point": "S", "weatherCode": "122", "weatherIconUrl": [{"value": "http://cdn.worldweatheronline.com/images/wsymbols01_png_64/wsymbol_0004_black_low_cloud.png"}], "weatherDesc": [{"value": "Overcast"}], "precipMM": "0.0", "precipInches": "0.0", "humidity": "82", "visibility": "10", "visibilityMiles": "6", "pressure": "1016", "pressureInches": "30", "cloudcover": "61", "HeatIndexC": "24", "HeatIndexF": "75", "DewPointC": "19", "DewPointF": "67", "WindChillC": "23", "WindChillF": "73", "WindGustMiles": "22", "WindGustKmph": "36", "FeelsLikeC": "24", "FeelsLikeF": "75", "uvIndex": "5"}]}]}}